{"success":true,"data":{"instrument":{"id":"inst_btcusd","symbol":"BTC/USD","name":"Bitcoin","type":"crypto","exchange":"Binance","sector":null,"industry":null,"currency":"USD","description":"Bitcoin is a decentralized digital currency and the first cryptocurrency, operating on a peer-to-peer network.","website":"https://bitcoin.org","logoUrl":null,"country":null,"price":{"current":74777.74,"previousClose":75736.82,"open":75736,"dayHigh":76278.36,"dayLow":74626.17,"change":-959.08,"changePercent":-1.26633,"lastUpdatedAt":"2026-04-19T20:35:34.163Z"},"volume":{"current":null,"average10d":null},"fundamentals":{"marketCap":null,"peRatio":null,"eps":null,"dividendYield":null},"marketStatus":"open","relatedInstruments":[]}}}